llm_gateway/__init__.py
llm_gateway/tools/__init__.py
llm_gateway/tools/llm_gateway_tool.py
llm_gateway/tools/utils.py
llm_gateway/yamls/llm_gateway_tool.yaml
tests/__init__.py
tests/test_llm_gateway_tool.py
llm_gateway-0.0.3.dist-info/METADATA
llm_gateway-0.0.3.dist-info/WHEEL
llm_gateway-0.0.3.dist-info/entry_points.txt
llm_gateway-0.0.3.dist-info/top_level.txt
llm_gateway-0.0.3.dist-info/RECORD
